dash_flask_login/__init__.py
dash_flask_login/flask_login_auth.py
dash_flask_login/version.py
dash_flask_login-0.0.7.dist-info/LICENSE.txt
dash_flask_login-0.0.7.dist-info/METADATA
dash_flask_login-0.0.7.dist-info/WHEEL
dash_flask_login-0.0.7.dist-info/top_level.txt
dash_flask_login-0.0.7.dist-info/RECORD
