Metadata-Version: 2.1
Name: dash-flask-login
Version: 0.0.7
Summary: Integration of Dash with Flask-Login
Home-page: https://github.com/gaw89/dash-flask-login
Author: Jeroen de Vries, gaw89
Author-email: jeroendevries@runbox.eu
License: UNKNOWN
Platform: UNKNOWN
Classifier: Intended Audience :: Developers
Classifier: Topic :: Utilities
Classifier: Natural Language :: English
Classifier: Operating System :: OS Independent
Classifier: License :: OSI Approved :: MIT License
Classifier: Programming Language :: Python :: 3
Classifier: Programming Language :: Python :: 3.9
Requires-Python: >=3.9
License-File: LICENSE.txt
Requires-Dist: dash (>=2.0.0)
Requires-Dist: flask-login (>=0.5.0)
